package_lib8127/__init__.py
package_lib8127/my_module.py
package_lib8127-0.1.dist-info/METADATA
package_lib8127-0.1.dist-info/WHEEL
package_lib8127-0.1.dist-info/top_level.txt
package_lib8127-0.1.dist-info/RECORD
