Metadata-Version: 2.1
Name: package_lib8127
Version: 0.1
Summary: A package that runs custom code on import.
Home-page: https://github.com/yourusername/my_package
Author: Your Name
Author-email: your.email@example.com
Classifier: Programming Language :: Python :: 3
Classifier: License :: OSI Approved :: MIT License
Classifier: Operating System :: OS Independent
Requires-Python: >=3.6
